splatter/__init__.py
splatter/distance_subgraph.py
splatter/generalized_star_clustering.py
splatter/swipe.py
splatter/umap.py
splatter/util.py
splatter-0.0.2.dist-info/LICENSE
splatter-0.0.2.dist-info/METADATA
splatter-0.0.2.dist-info/WHEEL
splatter-0.0.2.dist-info/top_level.txt
splatter-0.0.2.dist-info/RECORD
